encore/__init__.py
encore/__main__.py
encore/main.py
encore/analysis/__init__.py
encore/analysis/Cell-Assembly-Detection/assembly_activity.m
encore/analysis/Cell-Assembly-Detection/assembly_patterns.m
encore/analysis/Cell-Assembly-Detection/bin_shuffling.m
encore/analysis/Cell-Assembly-Detection/caller_1.m
encore/analysis/Cell-Assembly-Detection/circular_shift.m
encore/analysis/Cell-Assembly-Detection/fast_ica.m
encore/analysis/Cell-Assembly-Detection/shift_thetacycle.m
encore/analysis/Cell-Assembly-Detection/toy_simulation.m
encore/analysis/NeuralEnsembles/example_raster_2_ens_by_density_synth_ens.m
encore/analysis/NeuralEnsembles/AssemblyGui/AssemblyGui.m
encore/analysis/NeuralEnsembles/AssemblyGui/SaveFigures.m
encore/analysis/NeuralEnsembles/AssemblyGui/loadTSfromHdf5.m
encore/analysis/NeuralEnsembles/AssemblyGui/neuronRaster2EnsRaster.m
encore/analysis/NeuralEnsembles/AssemblyGui/othercolor.m
encore/analysis/NeuralEnsembles/AssemblyGui/plot_core_cells.m
encore/analysis/NeuralEnsembles/AssemblyGui/plot_delta_rho.m
encore/analysis/NeuralEnsembles/AssemblyGui/plot_eigs.m
encore/analysis/NeuralEnsembles/AssemblyGui/plot_ens_corr.m
encore/analysis/NeuralEnsembles/AssemblyGui/plot_ens_seq.m
encore/analysis/NeuralEnsembles/AssemblyGui/plot_pca.m
encore/analysis/NeuralEnsembles/AssemblyGui/plot_raster.m
encore/analysis/NeuralEnsembles/AssemblyGui/raster2ens_by_density.m
encore/analysis/NeuralEnsembles/AssemblyGui/redblue.m
encore/analysis/NeuralEnsembles/AssemblyGui/shuffle.m
encore/analysis/NeuralEnsembles/AssemblyGui/subSample_ensembles_pca.m
encore/analysis/NeuralEnsembles/AssemblyGui/analysis_codes/cluster_by_pow_fit.m
encore/analysis/NeuralEnsembles/AssemblyGui/analysis_codes/decisionGraph.m
encore/analysis/NeuralEnsembles/AssemblyGui/analysis_codes/delta_from_dist_mat.m
encore/analysis/NeuralEnsembles/AssemblyGui/analysis_codes/densityClust_fast.m
encore/analysis/NeuralEnsembles/AssemblyGui/analysis_codes/ens_raster_from_templates.m
encore_toolkit-2.1.0.dist-info/licenses/LICENSE
encore_toolkit-2.1.0.dist-info/METADATA
encore_toolkit-2.1.0.dist-info/WHEEL
encore_toolkit-2.1.0.dist-info/entry_points.txt
encore_toolkit-2.1.0.dist-info/top_level.txt
encore_toolkit-2.1.0.dist-info/RECORD
