Metadata-Version: 2.4
Name: encore-toolkit
Version: 2.1.0
Summary: GUI for Ensembles Comparison and Recognition
Author: Ricardo Velazquez Contreras
License-Expression: GPL-3.0-only
Project-URL: Homepage, https://github.com/rivelco/ENCORE
Project-URL: Documentation, https://rivelco.github.io/ENCORE/
Project-URL: Issues, https://github.com/rivelco/ENCORE/issues
Classifier: Development Status :: 4 - Beta
Classifier: Intended Audience :: Science/Research
Classifier: Topic :: Scientific/Engineering :: Bio-Informatics
Classifier: Topic :: Scientific/Engineering :: Medical Science Apps.
Classifier: Topic :: Scientific/Engineering :: Information Analysis
Classifier: Programming Language :: Python :: 3
Classifier: Programming Language :: Python :: 3 :: Only
Classifier: Programming Language :: Python :: 3.9
Classifier: Programming Language :: Python :: 3.10
Classifier: Programming Language :: Python :: 3.11
Classifier: Operating System :: OS Independent
Requires-Python: >=3.9
License-File: LICENSE
Requires-Dist: PyQt6>=6.0
Requires-Dist: numpy
Requires-Dist: matplotlib
Requires-Dist: scipy
Requires-Dist: h5py
Requires-Dist: scikit-learn
Requires-Dist: pyqtdarktheme
Requires-Dist: pyyaml
Requires-Dist: pydantic
Provides-Extra: dev
Requires-Dist: pyqt6-tools; extra == "dev"
Requires-Dist: pytest; extra == "dev"
Requires-Dist: build; extra == "dev"
Provides-Extra: docs
Requires-Dist: sphinx>=7.0; extra == "docs"
Requires-Dist: furo; extra == "docs"
Requires-Dist: sphinx-copybutton; extra == "docs"
Requires-Dist: sphinxcontrib-napoleon; extra == "docs"
Requires-Dist: sphinx-autodoc-typehints; extra == "docs"
Provides-Extra: all
Requires-Dist: pyqt6-tools; extra == "all"
Requires-Dist: pytest; extra == "all"
Requires-Dist: build; extra == "all"
Requires-Dist: sphinx>=7.0; extra == "all"
Requires-Dist: furo; extra == "all"
Requires-Dist: sphinx-copybutton; extra == "all"
Requires-Dist: sphinxcontrib-napoleon; extra == "all"
Requires-Dist: sphinx-autodoc-typehints; extra == "all"
Dynamic: license-file
